netbox_cable_labels/__init__.py
netbox_cable_labels/signals.py
netbox_cable_labels/utils.py
netbox_cable_labels/management/__init__.py
netbox_cable_labels/management/commands/__init__.py
netbox_cable_labels/management/commands/generate_labels.py
netbox_cable_labels/tests/__init__.py
netbox_cable_labels/tests/test_import.py
netbox_cable_labels/tests/test_management_command.py
netbox_cable_labels/tests/test_signals.py
netbox_cable_labels/tests/test_utils.py
netbox_cable_labels-0.1.0.dist-info/licenses/LICENSE
netbox_cable_labels-0.1.0.dist-info/METADATA
netbox_cable_labels-0.1.0.dist-info/WHEEL
netbox_cable_labels-0.1.0.dist-info/top_level.txt
netbox_cable_labels-0.1.0.dist-info/RECORD
