Metadata-Version: 2.4
Name: netbox-cable-labels
Version: 0.1.0
Summary: NetBox plugin for automatic cable label generation
Author: Jonathan Senecal
Author-email: Jonathan Senecal <contact@jonathansenecal.com>
License-Expression: Apache-2.0
Project-URL: Homepage, https://github.com/jsenecal/netbox-cable-labels
Project-URL: Repository, https://github.com/jsenecal/netbox-cable-labels.git
Project-URL: Issues, https://github.com/jsenecal/netbox-cable-labels/issues
Keywords: netbox,netbox-plugin,cable-management,labeling
Classifier: Development Status :: 4 - Beta
Classifier: Environment :: Plugins
Classifier: Framework :: Django
Classifier: Intended Audience :: System Administrators
Classifier: Operating System :: OS Independent
Classifier: Programming Language :: Python :: 3
Classifier: Programming Language :: Python :: 3.10
Classifier: Programming Language :: Python :: 3.11
Classifier: Programming Language :: Python :: 3.12
Classifier: Topic :: System :: Networking
Requires-Python: >=3.9
License-File: LICENSE
Dynamic: author
Dynamic: license-file
Dynamic: requires-python
